taozhibo/__init__.py
taozhibo/cli.py
taozhibo/taozhibo.py
taozhibo-0.1.0.dist-info/AUTHORS.rst
taozhibo-0.1.0.dist-info/LICENSE
taozhibo-0.1.0.dist-info/METADATA
taozhibo-0.1.0.dist-info/WHEEL
taozhibo-0.1.0.dist-info/entry_points.txt
taozhibo-0.1.0.dist-info/top_level.txt
taozhibo-0.1.0.dist-info/RECORD
